<?xml version="1.0" encoding="utf-8" ?><dwsync><file name="single-battle.js" server="ftp.lacremecreative.com/bg.lacremecreative.com/" local="3597708751" remote="3600036900" Dst="-1" /><file name="battle-vote.js" server="ftp.lacremecreative.com/bg.lacremecreative.com/" local="3599060216" remote="3600036900" Dst="-1" /><file name="editbattle.js" server="ftp.lacremecreative.com/bg.lacremecreative.com/" local="3597839655" remote="3600036900" Dst="-1" /><file name="battle.js" server="ftp.lacremecreative.com/bg.lacremecreative.com/" local="3598921665" remote="3600036900" Dst="-1" /><file name="single-battle.js" server="72.55.156.29/public_html/" local="3597708751" remote="3600189600" Dst="-1" /><file name="battle-vote.js" server="72.55.156.29/public_html/" local="3599060216" remote="3600189600" Dst="-1" /><file name="editbattle.js" server="72.55.156.29/public_html/" local="3601496669" remote="3601514640" Dst="-1" /><file name="battle.js" server="72.55.156.29/public_html/" local="3600611501" remote="3600638700" Dst="-1" /><file name="single-entry.js" server="72.55.156.29/public_html/" local="3601158666" remote="3601177320" Dst="-1" /></dwsync>